codex_linker/__init__.py
codex_linker/args.py
codex_linker/auth_flow.py
codex_linker/cli.py
codex_linker/config_utils.py
codex_linker/detect.py
codex_linker/doctor.py
codex_linker/emit.py
codex_linker/guided_pipeline.py
codex_linker/impl.py
codex_linker/io_safe.py
codex_linker/keychain.py
codex_linker/logging_utils.py
codex_linker/main_flow.py
codex_linker/migrate.py
codex_linker/output_writer.py
codex_linker/render.py
codex_linker/spec.py
codex_linker/state.py
codex_linker/ui.py
codex_linker/updates.py
codex_linker/utils.py
codex_linker/argsets/__init__.py
codex_linker/argsets/backups.py
codex_linker/argsets/files.py
codex_linker/argsets/general.py
codex_linker/argsets/mcp.py
codex_linker/argsets/model.py
codex_linker/argsets/other.py
codex_linker/argsets/profiles.py
codex_linker/argsets/providers.py
codex_linker/flows/__init__.py
codex_linker/flows/context_flow.py
codex_linker/flows/editor_flow.py
codex_linker/flows/model_flow.py
codex_linker/flows/provider_flow.py
codex_linker/flows/startup.py
codex_linker/flows/stateflow.py
codex_linker/flows/summary_flow.py
codex_linker/prompts/__init__.py
codex_linker/prompts/base_pick.py
codex_linker/prompts/hub.py
codex_linker/prompts/input_utils.py
codex_linker/prompts/mcp.py
codex_linker/prompts/profiles.py
codex_linker/prompts/profiles_edit.py
codex_linker/prompts/providers.py
codex_linker/updatesets/__init__.py
codex_linker/updatesets/check.py
codex_linker/updatesets/detect.py
codex_linker/updatesets/report.py
codex_linker/updatesets/sources.py
codex_linker/updatesets/types.py
codex_linker/updatesets/version.py
codex_cli_linker-0.2.0.dist-info/METADATA
codex_cli_linker-0.2.0.dist-info/WHEEL
codex_cli_linker-0.2.0.dist-info/entry_points.txt
codex_cli_linker-0.2.0.dist-info/top_level.txt
codex_cli_linker-0.2.0.dist-info/RECORD
