Metadata-Version: 2.4
Name: codex-cli-linker
Version: 0.2.0
Summary: Simple CLI that links Codex configuration to local servers
Author: Mariana
License-Expression: MIT
Requires-Python: >=3.8
Provides-Extra: dev
Requires-Dist: black; extra == "dev"
Requires-Dist: pytest; extra == "dev"
Requires-Dist: pytest-cov; extra == "dev"
Requires-Dist: pytest-timeout; extra == "dev"
Requires-Dist: ruff; extra == "dev"
